restless_haystack/__init__.py
restless_haystack/resources.py
restless_haystack-0.3.1.dist-info/DESCRIPTION.rst
restless_haystack-0.3.1.dist-info/METADATA
restless_haystack-0.3.1.dist-info/RECORD
restless_haystack-0.3.1.dist-info/WHEEL
restless_haystack-0.3.1.dist-info/metadata.json
restless_haystack-0.3.1.dist-info/top_level.txt
