Metadata-Version: 2.0
Name: restless-haystack
Version: 0.3.1
Summary: Integration of the Restless and Haystack libraries for Django
Home-page: https://github.com/CraveFood/restless-haystack
Author: Bruno Marques
Author-email: bruno@bmarques.net
License: MIT
Platform: UNKNOWN
Classifier: Development Status :: 1 - Planning
Classifier: Intended Audience :: Developers
Classifier: Topic :: Software Development :: Libraries :: Python Modules
Classifier: License :: OSI Approved :: MIT License
Classifier: Environment :: Web Environment
Classifier: Framework :: Django
Classifier: Programming Language :: Python :: 2
Classifier: Programming Language :: Python :: 3
Requires-Dist: Django
Requires-Dist: django-haystack
Requires-Dist: restless
